click_constrained_option/_ConstrainedOption.py
click_constrained_option/__init__.py
click_constrained_option/_version.py
click_constrained_option-0.1.dist-info/LICENSE
click_constrained_option-0.1.dist-info/METADATA
click_constrained_option-0.1.dist-info/WHEEL
click_constrained_option-0.1.dist-info/top_level.txt
click_constrained_option-0.1.dist-info/RECORD
