Metadata-Version: 2.1
Name: click-constrained-option
Version: 0.1
Summary: Constrained option support for click
Home-page: https://github.com/nobody-65534/click-constrained-option
License: BSD
Platform: UNKNOWN
Classifier: Development Status :: 4 - Beta
Classifier: Environment :: Console
Classifier: Intended Audience :: Developers
Classifier: License :: OSI Approved :: BSD License
Classifier: Programming Language :: Python :: 3
Requires-Dist: click (<8,>=7.0)
